web_scraping_bot_template/__init__.py
web_scraping_bot_template/test_bot_template.py
web_scraping_bot_template/web_scraping_bot_template.py
web_scraping_bot_template-1.2.0.dist-info/METADATA
web_scraping_bot_template-1.2.0.dist-info/WHEEL
web_scraping_bot_template-1.2.0.dist-info/top_level.txt
web_scraping_bot_template-1.2.0.dist-info/RECORD
