Metadata-Version: 2.1
Name: web-scraping-bot-template
Version: 1.2.0
Summary: Tools that are useful for building web-scraping automated bots.
Home-page: UNKNOWN
Author: Antonin GENElot<
Author-email: jaimelesfraisesbleues@gmail.com
License: UNKNOWN
Keywords: python,bot,automated,web-scraping,python bot
Platform: UNKNOWN
Classifier: Development Status :: 1 - Planning
Classifier: Intended Audience :: Developers
Classifier: Programming Language :: Python :: 3
Classifier: Operating System :: Unix
Classifier: Operating System :: MacOS :: MacOS X
Classifier: Operating System :: Microsoft :: Windows
Requires-Dist: requests
Requires-Dist: bs4
